Metadata-Version: 1.1
Name: pysqs
Version: 0.0
Summary: pysqs calculates simple quasirandom structures
Home-page: https://brandonbockund.com/
Author: Brandon Bocklund
Author-email: brandonbocklund@gmail.com
License: MIT
Platform: UNKNOWN
Classifier: Development Status :: 1 - Planning
Classifier: Intended Audience :: Science/Research
Classifier: License :: OSI Approved :: MIT License
Classifier: Programming Language :: Python :: 2
Classifier: Programming Language :: Python :: 3
